one_block/__init__.py
one_block/accessory/__init__.py
one_block/accessory/accessory.py
one_block/accessory/button.py
one_block/accessory/checkbox.py
one_block/accessory/option.py
one_block/accessory/overflow.py
one_block/accessory/picker.py
one_block/accessory/radio.py
one_block/accessory/selects.py
one_block/actions/__init__.py
one_block/actions/actions.py
one_block/base.py
one_block/context/__init__.py
one_block/context/context.py
one_block/divider/__init__.py
one_block/divider/plain.py
one_block/header/__init__.py
one_block/header/header.py
one_block/image/__init__.py
one_block/image/image.py
one_block/input_blocks/__init__.py
one_block/input_blocks/plain_text_input.py
one_block/input_blocks/selects.py
one_block/input_blocks/text_input.py
one_block/section/__init__.py
one_block/section/button.py
one_block/section/checkbox.py
one_block/section/image.py
one_block/section/markdown.py
one_block/section/overflow.py
one_block/section/picker.py
one_block/section/plain_text.py
one_block/section/radio_buttons.py
one_block/section/selects.py
one_block/section/text_fields.py
one_block-0.1.4.dist-info/LICENSE
one_block-0.1.4.dist-info/METADATA
one_block-0.1.4.dist-info/WHEEL
one_block-0.1.4.dist-info/RECORD
