Metadata-Version: 2.1
Name: one-block
Version: 0.1.4
Summary: An easy-to-use, opinionated slack blockkit implementation
License: MIT
Author: Dragos Dumitrache
Author-email: dragos@afterburner.dev
Requires-Python: >=3.10,<4.0
Classifier: License :: OSI Approved :: MIT License
Classifier: Programming Language :: Python :: 3
Classifier: Programming Language :: Python :: 3.10
Classifier: Programming Language :: Python :: 3.11
